mkdocs_submodule_edit_uri/__init__.py
mkdocs_submodule_edit_uri/plugin.py
mkdocs_submodule_edit_uri-1.1.0.dist-info/LICENSE
mkdocs_submodule_edit_uri-1.1.0.dist-info/METADATA
mkdocs_submodule_edit_uri-1.1.0.dist-info/WHEEL
mkdocs_submodule_edit_uri-1.1.0.dist-info/entry_points.txt
mkdocs_submodule_edit_uri-1.1.0.dist-info/top_level.txt
mkdocs_submodule_edit_uri-1.1.0.dist-info/RECORD
