Metadata-Version: 2.1
Name: mkdocs-submodule-edit-uri
Version: 1.1.0
Summary: A plugin to convert the edit_uri for GitHub submodules
Author-email: Sondre Grønås <mail@sondregronas.com>
License: MIT
Project-URL: homepage, https://github.com/sondregronas/mkdocs-submodule-edit-uri
Project-URL: documentation, https://github.com/sondregronas/mkdocs-submodule-edit-uri
Project-URL: repository, https://github.com/sondregronas/mkdocs-submodule-edit-uri
Project-URL: issues, https://github.com/sondregronas/mkdocs-submodule-edit-uri/issues
Project-URL: funding, https://github.com/sponsors/sondregronas
Keywords: mkdocs,markdown,submodules,github,edit_uri
Classifier: Development Status :: 5 - Production/Stable
Classifier: License :: OSI Approved :: MIT License
Classifier: Programming Language :: Python
Classifier: Programming Language :: Python :: 3
Classifier: Programming Language :: Python :: 3 :: Only
Classifier: Topic :: Documentation
Classifier: Topic :: Software Development :: Documentation
Requires-Python: >=3.8
License-File: LICENSE
Requires-Dist: mkdocs >=1
Provides-Extra: tests
Requires-Dist: pytest ; extra == 'tests'
